loader/__init__.py
loader/file_loader.py
mi_graph/__init__.py
mi_graph/api.py
mi_graph/knowledge_graph.py
mi_graph/pipeline.py
mi_graph/triple_generation.py
mi_graph/util.py
preprocess/__init__.py
preprocess/cleaner.py
preprocess/cleaner_imp.py
rdf_parser/__init__.py
rdf_parser/rdf_helper.py
rdf_parser/rdf_parser.py
resources/__init__.py
resources/error.py
resources/json_wrapper.py
resources/knowledgegraph_info_container.py
resources/knox_triples.py
resources/random_number_gen.py
resources/term_frequency.py
tests/__init__.py
tests/test_argsparser.py
tests/test_cleaner.py
tests/test_knowledgegraph.py
tests/test_loader.py
tests/test_model.py
tests/test_rdf_helper.py
tests/test_rdf_parser.py
tests/test_term_frequency.py
word_embedding/__init__.py
word_embedding/converter.py
word_embedding/dependency.py
word_embedding/grammarcategories.py
word_embedding/spacy_model.py
word_embedding/token.py
knox_mi_graph-1.1.2.dist-info/LICENSE
knox_mi_graph-1.1.2.dist-info/METADATA
knox_mi_graph-1.1.2.dist-info/WHEEL
knox_mi_graph-1.1.2.dist-info/entry_points.txt
knox_mi_graph-1.1.2.dist-info/top_level.txt
knox_mi_graph-1.1.2.dist-info/RECORD
