Metadata-Version: 2.1
Name: knox-mi-graph
Version: 1.1.2
Summary: Knowledge graph builder
Home-page: https://git.its.aau.dk/Knox/mi-graph
Author: Foersteholdet
Author-email: sw514e20@cs.aau.dk
License: UNKNOWN
Platform: UNKNOWN
Classifier: Programming Language :: Python :: 3
Classifier: License :: OSI Approved :: MIT License
Classifier: Operating System :: OS Independent
Requires-Python: >=3.8
Requires-Dist: pylint (~=2.6.0)
Requires-Dist: gensim (~=3.8.3)
Requires-Dist: matplotlib (~=3.3.2)
Requires-Dist: spacy (~=2.3.2)
Requires-Dist: networkx (~=2.5)
Requires-Dist: pandas (~=1.1.3)
Requires-Dist: numpy (~=1.19.3)
Requires-Dist: nltk (~=3.5)
Requires-Dist: rdflib (~=5.0.0)
Requires-Dist: pytest (~=6.1.2)
Requires-Dist: requests (~=2.24.0)
Requires-Dist: flask (~=1.1.2)
Requires-Dist: setuptools (~=50.3.1)
